{"Title":"Mad Dog and Glory","Year":"1993","Rated":"R","Released":"05 Mar 1993","Runtime":"97 min","Genre":"Comedy, Crime, Drama","Director":"John McNaughton","Writer":"Richard Price","Actors":"Robert De Niro, Uma Thurman, Bill Murray","Plot":"When shy, soft-spoken Chicago detective Wayne \u0022Mad Dog\u0022 Dobie inadvertently saves the life of local gangster Frank Milo, he\u0027s the reluctant recipient of an unusual one week \u0022thank you\u0022 gift - a beautiful bartender named Glory.","Language":"English","Awards":"2 nominations","Poster":"https://m.media-amazon.com/images/M/MV5BYWViMGIzMzktNDhjYS00ZjVhLWFjOWQtMjVlMmRhZjI5ZDlkXkEyXkFqcGdeQXVyNjUwNzk3NDc@._V1_SX300.jpg","Ratings":[{"Source":"Internet Movie Database","Value":"6.2/10"},{"Source":"Rotten Tomatoes","Value":"77%"},{"Source":"Metacritic","Value":"71/100"}],"Metascore":"71","imdbRating":"6.2","imdbVotes":"22,081","imdbID":"tt0107473","Type":"movie","DVD":"02 Mar 2004","Response":"True"}